setuptools_cmd_deps.py
setuptools_cmd_deps-1.0.1.dist-info/LICENSE
setuptools_cmd_deps-1.0.1.dist-info/METADATA
setuptools_cmd_deps-1.0.1.dist-info/WHEEL
setuptools_cmd_deps-1.0.1.dist-info/entry_points.txt
setuptools_cmd_deps-1.0.1.dist-info/top_level.txt
setuptools_cmd_deps-1.0.1.dist-info/RECORD
