Metadata-Version: 2.1
Name: setuptools-cmd-deps
Version: 1.0.1
Summary: setuptools plugin to configure the dependency among commands
Home-page: https://github.com/jameslan/setuptools-cmd-deps
Author: James Lan
Author-email: jameslan@gmail.com
License: Apache License 2.0
Platform: UNKNOWN
Classifier: Programming Language :: Python :: 3
Classifier: Programming Language :: Python :: 3.5
Classifier: Programming Language :: Python :: 3.6
Classifier: Programming Language :: Python :: 3.7
Classifier: Programming Language :: Python :: 3.8
Classifier: Intended Audience :: Developers
Classifier: License :: OSI Approved :: Apache Software License
Requires-Python: >=3.5
